{
    "タイムテーブル": [
        {
            "グループ名": "ラブアグレッション",
            "グループ名_採用": "ラブアグレッション",
            "ライブステージ": {
                "from": "09:55",
                "to": "11:10"
            },
            "備考": ""
        },
        {
            "グループ名": "えすれある",
            "グループ名_採用": "えすれある",
            "ライブステージ": {
                "from": "11:15",
                "to": "12:30"
            },
            "備考": ""
        },
        {
            "グループ名": "momograci",
            "グループ名_採用": "momograci",
            "ライブステージ": {
                "from": "12:35",
                "to": "13:50"
            },
            "備考": ""
        },
        {
            "グループ名": "Goodbye for First kiss",
            "グループ名_採用": "Goodbye for First kiss",
            "ライブステージ": {
                "from": "14:00",
                "to": "15:15"
            },
            "備考": ""
        },
        {
            "グループ名": "メリーパレード",
            "グループ名_採用": "メリーパレード",
            "ライブステージ": {
                "from": "15:20",
                "to": "16:35"
            },
            "備考": ""
        },
        {
            "グループ名": "カリギュラ",
            "グループ名_採用": "カリギュラ",
            "ライブステージ": {
                "from": "16:40",
                "to": "17:55"
            },
            "備考": ""
        },
        {
            "グループ名": "BABY BUBBLE",
            "グループ名_採用": "BABY BUBBLE",
            "ライブステージ": {
                "from": "18:00",
                "to": "19:15"
            },
            "備考": ""
        }
    ],
    "ステージ名": "特典会30"
}