{
    "タイムテーブル": [
        {
            "グループ名": "可憐なアイボリー",
            "グループ名_採用": "可憐なアイボリー",
            "ライブステージ": {
                "from": "13:15",
                "to": "13:40"
            },
            "備考": "",
            "出番ID": 85,
            "グループID": 125,
            "ステージID": 6
        },
        {
            "グループ名": "絶対少女",
            "グループ名_採用": "絶対少女",
            "ライブステージ": {
                "from": "13:40",
                "to": "14:05"
            },
            "備考": "",
            "出番ID": 86,
            "グループID": 137,
            "ステージID": 6
        },
        {
            "グループ名": "スーパーベイビーズ",
            "グループ名_採用": "スーパーベイビーズ",
            "ライブステージ": {
                "from": "14:10",
                "to": "14:35"
            },
            "備考": "",
            "出番ID": 87,
            "グループID": 103,
            "ステージID": 6
        },
        {
            "グループ名": "MEOWMEW",
            "グループ名_採用": "MEOWMEW",
            "ライブステージ": {
                "from": "14:35",
                "to": "15:00"
            },
            "備考": "",
            "出番ID": 88,
            "グループID": 32,
            "ステージID": 6
        },
        {
            "グループ名": "可愛いって言わないと呪う!",
            "グループ名_採用": "可愛いって言わないと呪う！",
            "ライブステージ": {
                "from": "15:05",
                "to": "15:30"
            },
            "備考": "",
            "出番ID": 89,
            "グループID": 124,
            "ステージID": 6
        },
        {
            "グループ名": "抜けてるくらいがちょうどいい",
            "グループ名_採用": "抜けてるくらいがちょうどいい",
            "ライブステージ": {
                "from": "15:30",
                "to": "15:55"
            },
            "備考": "",
            "出番ID": 90,
            "グループID": 130,
            "ステージID": 6
        },
        {
            "グループ名": "WT☆Egret",
            "グループ名_採用": "WT☆Egret",
            "ライブステージ": {
                "from": "16:00",
                "to": "16:25"
            },
            "備考": "",
            "出番ID": 91,
            "グループID": 62,
            "ステージID": 6
        },
        {
            "グループ名": "ワガママなラストノート",
            "グループ名_採用": "ワガママなラストノート",
            "ライブステージ": {
                "from": "16:25",
                "to": "16:50"
            },
            "備考": "",
            "出番ID": 92,
            "グループID": 122,
            "ステージID": 6
        },
        {
            "グループ名": "α+",
            "グループ名_採用": "α+",
            "ライブステージ": {
                "from": "16:55",
                "to": "17:20"
            },
            "備考": "",
            "出番ID": 93,
            "グループID": 77,
            "ステージID": 6
        },
        {
            "グループ名": "Bunny La Crew",
            "グループ名_採用": "Bunny La Crew",
            "ライブステージ": {
                "from": "17:20",
                "to": "17:45"
            },
            "備考": "",
            "出番ID": 94,
            "グループID": 11,
            "ステージID": 6
        },
        {
            "グループ名": "フューチャーサイダー",
            "グループ名_採用": "フューチャーサイダー",
            "ライブステージ": {
                "from": "17:50",
                "to": "18:15"
            },
            "備考": "",
            "出番ID": 95,
            "グループID": 111,
            "ステージID": 6
        },
        {
            "グループ名": "江戸桜",
            "グループ名_採用": "江戸桜",
            "ライブステージ": {
                "from": "18:15",
                "to": "18:40"
            },
            "備考": "",
            "出番ID": 96,
            "グループID": 134,
            "ステージID": 6
        },
        {
            "グループ名": "FULIT BOX",
            "グループ名_採用": "FULIT BOX",
            "ライブステージ": {
                "from": "18:45",
                "to": "19:10"
            },
            "備考": "",
            "出番ID": 97,
            "グループID": 19,
            "ステージID": 6
        },
        {
            "グループ名": "DREAMING MONSTER",
            "グループ名_採用": "DREAMING MONSTER",
            "ライブステージ": {
                "from": "19:10",
                "to": "19:35"
            },
            "備考": "",
            "出番ID": 98,
            "グループID": 15,
            "ステージID": 6
        },
        {
            "グループ名": "ルルネージュ",
            "グループ名_採用": "ルルネージュ",
            "ライブステージ": {
                "from": "19:35",
                "to": "20:00"
            },
            "備考": "",
            "出番ID": 99,
            "グループID": 121,
            "ステージID": 6
        }
    ],
    "ステージ名": "シアターマーキュリー新宿"
}