{
    "タイムテーブル": [
        {
            "グループ名": "Ange☆Reve",
            "ライブステージ": {
                "from": "10:05",
                "to": "10:25"
            },
            "グループ名_修正候補": "Ange☆Reve"
        },
        {
            "グループ名": "I'mew（あいみゅう）",
            "ライブステージ": {
                "from": "10:25",
                "to": "10:45"
            },
            "グループ名_修正候補": "I’mew（あいみゅう）"
        },
        {
            "グループ名": "OS☆U",
            "ライブステージ": {
                "from": "10:45",
                "to": "11:05"
            },
            "グループ名_修正候補": "OS☆U"
        },
        {
            "グループ名": "321 アイドル部",
            "ライブステージ": {
                "from": "11:05",
                "to": "11:25"
            },
            "グループ名_修正候補": "LSアイドル21"
        },
        {
            "グループ名": "パラディーク",
            "ライブステージ": {
                "from": "11:25",
                "to": "11:45"
            },
            "グループ名_修正候補": "パラディーク"
        },
        {
            "グループ名": "キミイロプロジェクト",
            "ライブステージ": {
                "from": "12:00",
                "to": "12:20"
            },
            "グループ名_修正候補": "キミイロプロジェクト"
        },
        {
            "グループ名": "Hey!Mommy!",
            "ライブステージ": {
                "from": "12:20",
                "to": "12:40"
            },
            "グループ名_修正候補": "Hey!Mommy!"
        },
        {
            "グループ名": "テンシメシ໒3",
            "ライブステージ": {
                "from": "12:40",
                "to": "13:00"
            },
            "グループ名_修正候補": "テンシメシ໒꒱"
        },
        {
            "グループ名": "おちゃメンタル☆パーティー",
            "ライブステージ": {
                "from": "13:00",
                "to": "13:20"
            },
            "グループ名_修正候補": "おちゃメンタル☆パーティー"
        },
        {
            "グループ名": "シンデレラ宣言！",
            "ライブステージ": {
                "from": "13:20",
                "to": "13:40"
            },
            "グループ名_修正候補": "シンデレラ宣言！"
        },
        {
            "グループ名": "Sweet Alley",
            "ライブステージ": {
                "from": "13:55",
                "to": "14:15"
            },
            "グループ名_修正候補": "Sweet Alley"
        },
        {
            "グループ名": "CUTIE STREET",
            "ライブステージ": {
                "from": "14:15",
                "to": "14:35"
            },
            "グループ名_修正候補": "COTO☆COTO CUTE"
        },
        {
            "グループ名": "結音 YUION",
            "ライブステージ": {
                "from": "14:35",
                "to": "14:55"
            },
            "グループ名_修正候補": "結音 YUION"
        },
        {
            "グループ名": "LarmeR",
            "ライブステージ": {
                "from": "14:55",
                "to": "15:15"
            },
            "グループ名_修正候補": "LarmeR"
        },
        {
            "グループ名": "マジカル・パンチライン",
            "ライブステージ": {
                "from": "15:15",
                "to": "15:35"
            },
            "グループ名_修正候補": "マジカル・パンチライン"
        },
        {
            "グループ名": "りんご娘",
            "ライブステージ": {
                "from": "15:50",
                "to": "16:10"
            },
            "グループ名_修正候補": "りんご娘"
        },
        {
            "グループ名": "BANZAI JAPAN",
            "ライブステージ": {
                "from": "16:10",
                "to": "16:30"
            },
            "グループ名_修正候補": "BANZAI JAPAN"
        },
        {
            "グループ名": "虹色の飛行少女",
            "ライブステージ": {
                "from": "16:30",
                "to": "16:50"
            },
            "グループ名_修正候補": "虹色の飛行少女"
        },
        {
            "グループ名": "Task have Fun",
            "ライブステージ": {
                "from": "16:50",
                "to": "17:10"
            },
            "グループ名_修正候補": "Task have Fun"
        },
        {
            "グループ名": "LinQ",
            "ライブステージ": {
                "from": "17:10",
                "to": "17:30"
            },
            "グループ名_修正候補": "LinQ"
        },
        {
            "グループ名": "ギガ LOVE アップビート",
            "ライブステージ": {
                "from": "17:45",
                "to": "18:05"
            },
            "グループ名_修正候補": "ギガLOVEアップビート"
        },
        {
            "グループ名": "純情のアフィリア",
            "ライブステージ": {
                "from": "18:05",
                "to": "18:25"
            },
            "グループ名_修正候補": "純情のアフィリア"
        },
        {
            "グループ名": "alma",
            "ライブステージ": {
                "from": "18:25",
                "to": "18:45"
            },
            "グループ名_修正候補": "alma"
        },
        {
            "グループ名": "メイビー ME",
            "ライブステージ": {
                "from": "18:45",
                "to": "19:05"
            },
            "グループ名_修正候補": "メイビーME"
        },
        {
            "グループ名": "Luce Twinkle Wink☆",
            "ライブステージ": {
                "from": "19:20",
                "to": "19:40"
            },
            "グループ名_修正候補": "Luce Twinkle Wink☆"
        },
        {
            "グループ名": "FRUITS ZIPPER",
            "ライブステージ": {
                "from": "19:40",
                "to": "20:00"
            },
            "グループ名_修正候補": "FRUITS ZIPPER"
        }
    ],
    "ステージ名": "ステージ2"
}