{
    "タイムテーブル": [
        {
            "グループ名": "透色ドロップ",
            "グループ名_採用": "透色ドロップ",
            "ライブステージ": {
                "from": "12:25",
                "to": "13:40"
            },
            "ステージID": 7,
            "備考": "",
            "出番ID": 126,
            "グループID": 114
        },
        {
            "グループ名": "クマリデパート",
            "グループ名_採用": "クマリデパート",
            "ライブステージ": {
                "from": "13:55",
                "to": "15:10"
            },
            "ステージID": 7,
            "備考": "",
            "出番ID": 127,
            "グループID": 86
        },
        {
            "グループ名": "SITUASION",
            "グループ名_採用": "SITUASION",
            "ライブステージ": {
                "from": "15:30",
                "to": "16:45"
            },
            "ステージID": 7,
            "備考": "",
            "出番ID": 128,
            "グループID": 119
        },
        {
            "グループ名": "CYNHN",
            "グループ名_採用": "CYNHN",
            "ライブステージ": {
                "from": "17:00",
                "to": "18:15"
            },
            "ステージID": 7,
            "備考": "",
            "出番ID": 129,
            "グループID": 10
        },
        {
            "グループ名": "ukka",
            "グループ名_採用": "ukka",
            "ライブステージ": {
                "from": "18:20",
                "to": "19:35"
            },
            "ステージID": 7,
            "備考": "",
            "出番ID": 130,
            "グループID": 66
        },
        {
            "グループ名": "FESTIVE",
            "グループ名_採用": "FES☆TIVE",
            "ライブステージ": {
                "from": "19:40",
                "to": "20:55"
            },
            "ステージID": 7,
            "備考": "",
            "出番ID": 131,
            "グループID": 12
        },
        {
            "グループ名": "BLACKNAZARENE",
            "グループ名_採用": "BLACKNAZARENE",
            "ライブステージ": {
                "from": "21:00",
                "to": "22:15"
            },
            "ステージID": 7,
            "備考": "",
            "出番ID": 132,
            "グループID": 7
        }
    ],
    "ステージ名": "特典会B（O-EAST2F）"
}