{
    "タイムテーブル": [
        {
            "グループ名": "PLATINUM Princes 研究生",
            "グループ名_採用": "PLATINUM Princess 研究生",
            "ライブステージ": {
                "from": "12:55",
                "to": "14:05"
            },
            "備考": ""
        },
        {
            "グループ名": "透色ドロップ",
            "グループ名_採用": "透色ドロップ",
            "ライブステージ": {
                "from": "14:10",
                "to": "15:20"
            },
            "備考": ""
        },
        {
            "グループ名": "可憐なアイボリー",
            "グループ名_採用": "可憐なアイボリー",
            "ライブステージ": {
                "from": "15:30",
                "to": "16:40"
            },
            "備考": ""
        },
        {
            "グループ名": "煌めき☆アンフォレント",
            "グループ名_採用": "煌めき☆アンフォレント",
            "ライブステージ": {
                "from": "16:45",
                "to": "17:55"
            },
            "備考": ""
        },
        {
            "グループ名": "AOAO",
            "グループ名_採用": "AOAO",
            "ライブステージ": {
                "from": "18:05",
                "to": "19:15"
            },
            "備考": ""
        },
        {
            "グループ名": "fav me",
            "グループ名_採用": "fav me",
            "ライブステージ": {
                "from": "19:25",
                "to": "20:35"
            },
            "備考": ""
        }
    ],
    "ステージ名": "特典会A：ATOM 4F"
}