{
    "タイムテーブル": [
        {
            "グループ名": "Peel the Apple",
            "グループ名_修正候補": "Peel the Apple",
            "ライブステージ": {
                "from": "10:00",
                "to": "10:15"
            }
        },
        {
            "グループ名": "alma",
            "グループ名_修正候補": "alma",
            "ライブステージ": {
                "from": "10:15",
                "to": "10:30"
            }
        },
        {
            "グループ名": "ステーチスのラブレター",
            "グループ名_修正候補": "ステーチスのラブレター",
            "ライブステージ": {
                "from": "10:30",
                "to": "10:45"
            }
        },
        {
            "グループ名": "UP ローチ",
            "グループ名_修正候補": "UPローチ",
            "ライブステージ": {
                "from": "10:45",
                "to": "11:00"
            }
        },
        {
            "グループ名": "ネコプラ pixx.",
            "グループ名_修正候補": "ネコプラpixx.",
            "ライブステージ": {
                "from": "11:00",
                "to": "11:15"
            }
        },
        {
            "グループ名": "すてねこキャッツ",
            "グループ名_修正候補": "すてねこキャッツ",
            "ライブステージ": {
                "from": "11:25",
                "to": "11:40"
            }
        },
        {
            "グループ名": "CANDY TUNE",
            "グループ名_修正候補": "CANDY TUNE",
            "ライブステージ": {
                "from": "11:40",
                "to": "11:55"
            }
        },
        {
            "グループ名": "九州女子翼",
            "グループ名_修正候補": "九州女子翼",
            "ライブステージ": {
                "from": "11:55",
                "to": "12:10"
            }
        },
        {
            "グループ名": "ミームトーキョー",
            "グループ名_修正候補": "ミームトーキョー",
            "ライブステージ": {
                "from": "12:10",
                "to": "12:25"
            }
        },
        {
            "グループ名": "アップアップガールズ（２）",
            "グループ名_修正候補": "アップアップガールズ（２）",
            "ライブステージ": {
                "from": "12:25",
                "to": "12:40"
            }
        },
        {
            "グループ名": "I to U $CREAMing!!",
            "グループ名_修正候補": "I to U $CREAMing!!",
            "ライブステージ": {
                "from": "12:50",
                "to": "13:05"
            }
        },
        {
            "グループ名": "@JAM EXPO 特別企画 -情熱のストロベリー-",
            "グループ名_修正候補": "@JAM EXPO 特別企画 -情熱のストロベリー-",
            "ライブステージ": {
                "from": "13:05",
                "to": "13:15"
            }
        },
        {
            "グループ名": "上月せれな",
            "グループ名_修正候補": "上月せれな",
            "ライブステージ": {
                "from": "13:15",
                "to": "13:30"
            }
        },
        {
            "グループ名": "開歌-かいか-",
            "グループ名_修正候補": "開歌-かいか-",
            "ライブステージ": {
                "from": "13:30",
                "to": "13:45"
            }
        },
        {
            "グループ名": "fishbowl",
            "グループ名_修正候補": "fishbowl",
            "ライブステージ": {
                "from": "13:45",
                "to": "14:00"
            }
        },
        {
            "グループ名": "×純文学少女歌劇団",
            "グループ名_修正候補": "×純文学少女歌劇団",
            "ライブステージ": {
                "from": "14:10",
                "to": "14:25"
            }
        },
        {
            "グループ名": "キミイロプロジェクト",
            "グループ名_修正候補": "キミイロプロジェクト",
            "ライブステージ": {
                "from": "14:25",
                "to": "14:40"
            }
        },
        {
            "グループ名": "美味しい曖昧",
            "グループ名_修正候補": "美味しい曖昧",
            "ライブステージ": {
                "from": "14:40",
                "to": "14:55"
            }
        },
        {
            "グループ名": "ゆるめるモ!",
            "グループ名_修正候補": "ゆるめるモ！",
            "ライブステージ": {
                "from": "14:55",
                "to": "15:10"
            }
        },
        {
            "グループ名": "夜光性アミューズ",
            "グループ名_修正候補": "夜光性アミューズ",
            "ライブステージ": {
                "from": "15:10",
                "to": "15:25"
            }
        },
        {
            "グループ名": "AVAM",
            "グループ名_修正候補": "AVAM",
            "ライブステージ": {
                "from": "15:40",
                "to": "15:55"
            }
        },
        {
            "グループ名": "@JAM アイドルアカデミー ステージ",
            "グループ名_修正候補": "@JAM アイドルアカデミー ステージ",
            "ライブステージ": {
                "from": "15:55",
                "to": "16:10"
            }
        },
        {
            "グループ名": "可憐なアイボリー",
            "グループ名_修正候補": "可憐なアイボリー",
            "ライブステージ": {
                "from": "16:10",
                "to": "16:25"
            }
        },
        {
            "グループ名": "my fav",
            "グループ名_修正候補": "my fav",
            "ライブステージ": {
                "from": "16:25",
                "to": "16:40"
            }
        },
        {
            "グループ名": "まねきケチャ",
            "グループ名_修正候補": "まねきケチャ",
            "ライブステージ": {
                "from": "16:40",
                "to": "16:55"
            }
        },
        {
            "グループ名": "JAPANARIZM",
            "グループ名_修正候補": "JAPANARIZM",
            "ライブステージ": {
                "from": "17:05",
                "to": "17:20"
            }
        },
        {
            "グループ名": "さとりモンスター",
            "グループ名_修正候補": "さとりモンスター",
            "ライブステージ": {
                "from": "17:20",
                "to": "17:35"
            }
        },
        {
            "グループ名": "HelloYouth",
            "グループ名_修正候補": "HelloYouth",
            "ライブステージ": {
                "from": "17:35",
                "to": "17:50"
            }
        },
        {
            "グループ名": "from ミクチャステージ",
            "グループ名_修正候補": "from ミクチャステージ",
            "ライブステージ": {
                "from": "17:50",
                "to": "18:05"
            }
        },
        {
            "グループ名": "Palette Parade",
            "グループ名_修正候補": "Palette Parade",
            "ライブステージ": {
                "from": "18:05",
                "to": "18:20"
            }
        },
        {
            "グループ名": "WT☆Egret",
            "グループ名_修正候補": "WT☆Egret",
            "ライブステージ": {
                "from": "18:20",
                "to": "18:35"
            }
        },
        {
            "グループ名": "@JAM EXPO 特別企画 -黒髪をなびかせて-",
            "グループ名_修正候補": "@JAM EXPO 特別企画 -黒髪をなびかせて-",
            "ライブステージ": {
                "from": "18:45",
                "to": "18:55"
            }
        },
        {
            "グループ名": "手羽先センセーション",
            "グループ名_修正候補": "手羽先センセーション",
            "ライブステージ": {
                "from": "18:55",
                "to": "19:10"
            }
        },
        {
            "グループ名": "パラディーク",
            "グループ名_修正候補": "パラディーク",
            "ライブステージ": {
                "from": "19:10",
                "to": "19:25"
            }
        },
        {
            "グループ名": "THE ORCHESTRA TOKYO",
            "グループ名_修正候補": "THE ORCHESTRA TOKYO",
            "ライブステージ": {
                "from": "19:25",
                "to": "19:40"
            }
        },
        {
            "グループ名": "Ringwanderung",
            "グループ名_修正候補": "Ringwanderung",
            "ライブステージ": {
                "from": "19:40",
                "to": "19:55"
            }
        },
        {
            "グループ名": "Task have Fun",
            "グループ名_修正候補": "Task have Fun",
            "ライブステージ": {
                "from": "19:55",
                "to": "20:10"
            }
        }
    ],
    "ステージ名": "ステージ5"
}