{
    "タイムテーブル": [
        {
            "グループ名": "[eN]",
            "ライブステージ": {
                "from": "12:20",
                "to": "13:35"
            },
            "グループ名_採用": "【eN】"
        },
        {
            "グループ名": "ポラライト",
            "ライブステージ": {
                "from": "13:45",
                "to": "15:00"
            },
            "グループ名_採用": "ポラライト"
        },
        {
            "グループ名": "W.ダブルヴィー",
            "ライブステージ": {
                "from": "15:05",
                "to": "16:20"
            },
            "グループ名_採用": "W.ダブルヴィー"
        },
        {
            "グループ名": "みらくる★ふぉーぜ",
            "ライブステージ": {
                "from": "16:30",
                "to": "17:45"
            },
            "グループ名_採用": "みらくる★ふぉーぜ"
        },
        {
            "グループ名": "SAISON",
            "ライブステージ": {
                "from": "17:55",
                "to": "19:10"
            },
            "グループ名_採用": "SAISON"
        }
    ],
    "ステージ名": "特典会10"
}